<annotation>
	<folder></folder>
	<filename>analysisVideo_ewcy6SDquEptdegDH_2mrHd9s4qun78LQQ7_13_jpg.rf.8f37da6bad0d6707fe9a51037dd16835.jpg</filename>
	<path>analysisVideo_ewcy6SDquEptdegDH_2mrHd9s4qun78LQQ7_13_jpg.rf.8f37da6bad0d6707fe9a51037dd16835.jpg</path>
	<source>
		<database>roboflow.ai</database>
	</source>
	<size>
		<width>720</width>
		<height>480</height>
		<depth>3</depth>
	</size>
	<segmented>0</segmented>
	<object>
		<name>lower_body</name>
		<pose>Unspecified</pose>
		<truncated>0</truncated>
		<difficult>0</difficult>
		<occluded>0</occluded>
		<bndbox>
			<xmin>182</xmin>
			<xmax>652</xmax>
			<ymin>291</ymin>
			<ymax>435</ymax>
		</bndbox>
	</object>
</annotation>
