<annotation>
	<folder></folder>
	<filename>analysisVideo_6maindLGo5nLQChyC_4Z5sRKAPJYnTinCHS_12_jpg.rf.bd72cd70a2c59c79756939588c73a36d.jpg</filename>
	<path>analysisVideo_6maindLGo5nLQChyC_4Z5sRKAPJYnTinCHS_12_jpg.rf.bd72cd70a2c59c79756939588c73a36d.jpg</path>
	<source>
		<database>roboflow.ai</database>
	</source>
	<size>
		<width>720</width>
		<height>480</height>
		<depth>3</depth>
	</size>
	<segmented>0</segmented>
	<object>
		<name>lowerbody</name>
		<pose>Unspecified</pose>
		<truncated>0</truncated>
		<difficult>0</difficult>
		<occluded>0</occluded>
		<bndbox>
			<xmin>103</xmin>
			<xmax>623</xmax>
			<ymin>168</ymin>
			<ymax>455</ymax>
		</bndbox>
	</object>
</annotation>
