<annotation>
	<folder></folder>
	<filename>analysisVideo_8vKudGXGevdRoxLYw_gyeSoPDqDhHxoviH7_20_jpg.rf.5e09629d9e007eb561b62e919cda0d27.jpg</filename>
	<path>analysisVideo_8vKudGXGevdRoxLYw_gyeSoPDqDhHxoviH7_20_jpg.rf.5e09629d9e007eb561b62e919cda0d27.jpg</path>
	<source>
		<database>roboflow.ai</database>
	</source>
	<size>
		<width>720</width>
		<height>480</height>
		<depth>3</depth>
	</size>
	<segmented>0</segmented>
	<object>
		<name>lower_body</name>
		<pose>Unspecified</pose>
		<truncated>0</truncated>
		<difficult>0</difficult>
		<occluded>0</occluded>
		<bndbox>
			<xmin>81</xmin>
			<xmax>520</xmax>
			<ymin>156</ymin>
			<ymax>379</ymax>
		</bndbox>
	</object>
</annotation>
