<annotation>
	<folder></folder>
	<filename>analysisVideo_5zbyXpojuQJZgNe8u_sxqhn2xoDTjeqxkK2_11_jpg.rf.f9b52473a84386f135a6d4b8cee86390.jpg</filename>
	<path>analysisVideo_5zbyXpojuQJZgNe8u_sxqhn2xoDTjeqxkK2_11_jpg.rf.f9b52473a84386f135a6d4b8cee86390.jpg</path>
	<source>
		<database>roboflow.ai</database>
	</source>
	<size>
		<width>720</width>
		<height>480</height>
		<depth>3</depth>
	</size>
	<segmented>0</segmented>
	<object>
		<name>lowerbody</name>
		<pose>Unspecified</pose>
		<truncated>0</truncated>
		<difficult>0</difficult>
		<occluded>0</occluded>
		<bndbox>
			<xmin>94</xmin>
			<xmax>644</xmax>
			<ymin>123</ymin>
			<ymax>424</ymax>
		</bndbox>
	</object>
</annotation>
